snakeskin/__init__.py
snakeskin/cli.py
snakeskin/framework.py
snakeskin/integrations.py
snakeskin/server.py
snakeskin/utils.py
snakeskin_xplnhub-1.0.2.dist-info/LICENSE
snakeskin_xplnhub-1.0.2.dist-info/METADATA
snakeskin_xplnhub-1.0.2.dist-info/WHEEL
snakeskin_xplnhub-1.0.2.dist-info/top_level.txt
snakeskin_xplnhub-1.0.2.dist-info/RECORD
