Metadata-Version: 2.2
Name: snakeskin-xplnhub
Version: 1.0.2
Summary: A modern, lightweight frontend framework for building component-based web applications
Home-page: https://github.com/XplnHUB/xplnhub-snakeskin
Author: Arpit Sarang
Author-email: info@snakeskin-framework.dev
License: MIT
Project-URL: Documentation, https://github.com/XplnHUB/xplnhub-snakeskin/tree/main/docs
Project-URL: Bug Reports, https://github.com/XplnHUB/xplnhub-snakeskin/issues
Project-URL: Source Code, https://github.com/XplnHUB/xplnhub-snakeskin
Keywords: web,frontend,framework,component,ui,tailwind,bootstrap,modular,site-generation
Classifier: Development Status :: 4 - Beta
Classifier: Intended Audience :: Developers
Classifier: License :: OSI Approved :: MIT License
Classifier: Programming Language :: Python :: 3
Classifier: Programming Language :: Python :: 3.8
Classifier: Programming Language :: Python :: 3.9
Classifier: Programming Language :: Python :: 3.10
Classifier: Programming Language :: Python :: 3.11
Classifier: Programming Language :: Python :: 3.12
Classifier: Topic :: Software Development :: Libraries :: Application Frameworks
Classifier: Topic :: Software Development :: User Interfaces
Classifier: Topic :: Internet :: WWW/HTTP :: Dynamic Content
Requires-Python: >=3.8
License-File: LICENSE
Requires-Dist: rich
Requires-Dist: typer
Requires-Dist: watchdog
Requires-Dist: websockets
Requires-Dist: click
Requires-Dist: markdown-it-py
Requires-Dist: shellingham
Dynamic: author
Dynamic: author-email
Dynamic: classifier
Dynamic: description
Dynamic: description-content-type
Dynamic: home-page
Dynamic: keywords
Dynamic: license
Dynamic: project-url
Dynamic: requires-dist
Dynamic: requires-python
Dynamic: summary
